gfamap/__init__.py
gfamap/gfamap.py
gfamap-0.2.3.dist-info/LICENSE
gfamap-0.2.3.dist-info/METADATA
gfamap-0.2.3.dist-info/WHEEL
gfamap-0.2.3.dist-info/entry_points.txt
gfamap-0.2.3.dist-info/top_level.txt
gfamap-0.2.3.dist-info/RECORD
