Metadata-Version: 2.1
Name: gfamap
Version: 0.2.3
Summary: Map edges of a genome graph to a reference genome database.
Home-page: https://github.com/jleechung/gfamap
Author: Joseph Lee
Author-email: joseph.lee@u.nus.edu
License: MIT
Keywords: python genome graph genome assembly
Platform: UNKNOWN
